README.md
setup.cfg
setup.py
src/snacks/__init__.py
src/snacks/rabbit.py
src/snacks.egg-info/PKG-INFO
src/snacks.egg-info/SOURCES.txt
src/snacks.egg-info/dependency_links.txt
src/snacks.egg-info/not-zip-safe
src/snacks.egg-info/requires.txt
src/snacks.egg-info/top_level.txt
test/tests.py