Metadata-Version: 2.1
Name: snacks
Version: 0.3.6
Summary: Wrapper to pika for an easy to use RabbitMQ interface.
Home-page: https://gitlab.com/mburkard/snacks
Author: Matthew Burkard
Author-email: matthewburkard@gmail.com
License: GNU General Public License v3 (GPLv3)
Platform: UNKNOWN
Classifier: Programming Language :: Python :: 3
Classifier: License :: OSI Approved :: GNU General Public License v3 (GPLv3)
